ceci/__init__.py
ceci/launchers.py
ceci/main.py
ceci/pipeline.py
ceci/stage.py
ceci-0.0.1.dist-info/DESCRIPTION.rst
ceci-0.0.1.dist-info/METADATA
ceci-0.0.1.dist-info/RECORD
ceci-0.0.1.dist-info/WHEEL
ceci-0.0.1.dist-info/entry_points.txt
ceci-0.0.1.dist-info/metadata.json
ceci-0.0.1.dist-info/top_level.txt
ceci_example/__init__.py
ceci_example/__main__.py
ceci_example/example_stages.py
ceci_example/types.py
